foundationallm_agent_plugins_experimental/__init__.py
foundationallm_agent_plugins_experimental/tool_plugin_manager.py
foundationallm_agent_plugins_experimental/_metadata/foundationallm_manifest.json
foundationallm_agent_plugins_experimental/tools/__init__.py
foundationallm_agent_plugins_experimental/tools/foundationallm_nop_tool.py
foundationallm_agent_plugins_experimental/tools/foundationallm_nop_tool_input.py
foundationallm_agent_plugins_experimental-0.9.7.post10.dist-info/METADATA
foundationallm_agent_plugins_experimental-0.9.7.post10.dist-info/WHEEL
foundationallm_agent_plugins_experimental-0.9.7.post10.dist-info/top_level.txt
foundationallm_agent_plugins_experimental-0.9.7.post10.dist-info/RECORD
